{
  "v": "5.9.6",
  "fr": 29.9700012207031,
  "ip": 0,
  "op": 12.00000048877,
  "w": 240,
  "h": 240,
  "nm": "안드팀4",
  "ddd": 0,
  "assets": [],
  "layers": [
    {
      "ddd": 0,
      "ind": 1,
      "ty": 4,
      "nm": "Layer 3 Outlines",
      "sr": 1,
      "ks": {
        "o": { "a": 0, "k": 100, "ix": 11 },
        "r": { "a": 0, "k": 0, "ix": 10 },
        "p": { "s": true, "x": { "a": 0, "k": 120, "ix": 3 }, "y": { "a": 0, "k": 120, "ix": 4 } },
        "a": { "a": 0, "k": [120, 120, 0], "ix": 1, "l": 2 },
        "s": { "a": 0, "k": [100, 100, 100], "ix": 6, "l": 2 }
      },
      "ao": 0,
      "shapes": [
        {
          "ty": "gr",
          "it": [
            {
              "ind": 0,
              "ty": "sh",
              "ix": 1,
              "ks": {
                "a": 0,
                "k": {
                  "i": [
                    [0.625, 7.459],
                    [-0.336, 2.113],
                    [-3.147, 0.132],
                    [-0.496, -3.134],
                    [0.015, -8.474],
                    [4.344, -0.155],
                    [0.48, 3.765]
                  ],
                  "o": [
                    [0.058, -0.98],
                    [0.513, -3.227],
                    [3.172, -0.133],
                    [1.323, 8.353],
                    [-0.007, 3.827],
                    [-4.321, 0.155],
                    [-0.797, -6.248]
                  ],
                  "v": [
                    [-7.486, -8.042],
                    [-7.137, -13.309],
                    [-1.282, -18.397],
                    [4.934, -13.764],
                    [7.471, 11.465],
                    [1.174, 18.375],
                    [-5.734, 11.973]
                  ],
                  "c": true
                },
                "ix": 2
              },
              "nm": "Path 1",
              "mn": "ADBE Vector Shape - Group",
              "hd": false
            },
            {
              "ty": "fl",
              "c": { "a": 0, "k": [0.992156922583, 0.992156922583, 0.992156922583, 1], "ix": 4 },
              "o": { "a": 0, "k": 100, "ix": 5 },
              "r": 1,
              "bm": 0,
              "nm": "Fill 1",
              "mn": "ADBE Vector Graphic - Fill",
              "hd": false
            },
            {
              "ty": "tr",
              "p": { "a": 0, "k": [71.06, 172.744], "ix": 2 },
              "a": { "a": 0, "k": [0, 0], "ix": 1 },
              "s": { "a": 0, "k": [100, 100], "ix": 3 },
              "r": { "a": 0, "k": 0, "ix": 6 },
              "o": { "a": 0, "k": 100, "ix": 7 },
              "sk": { "a": 0, "k": 0, "ix": 4 },
              "sa": { "a": 0, "k": 0, "ix": 5 },
              "nm": "Transform"
            }
          ],
          "nm": "Group 1",
          "np": 2,
          "cix": 2,
          "bm": 0,
          "ix": 1,
          "mn": "ADBE Vector Group",
          "hd": false
        },
        {
          "ty": "gr",
          "it": [
            {
              "ind": 0,
              "ty": "sh",
              "ix": 1,
              "ks": {
                "a": 0,
                "k": {
                  "i": [
                    [0, 3.995],
                    [0.809, 6.626],
                    [-3.824, 0.672],
                    [-1.017, -5.622],
                    [0.325, -11.478],
                    [3.888, 0.152],
                    [0.101, 4.812]
                  ],
                  "o": [
                    [0.773, -6.677],
                    [-0.663, -5.428],
                    [4.045, -0.711],
                    [2.06, 11.39],
                    [-0.132, 4.677],
                    [-3.922, -0.153],
                    [-0.084, -3.993]
                  ],
                  "v": [
                    [-6.66, 5.01],
                    [-7.208, -14.924],
                    [-2.198, -24.377],
                    [5.811, -16.795],
                    [7.104, 17.589],
                    [-0.106, 24.937],
                    [-6.643, 16.993]
                  ],
                  "c": true
                },
                "ix": 2
              },
              "nm": "Path 1",
              "mn": "ADBE Vector Shape - Group",
              "hd": false
            },
            {
              "ty": "fl",
              "c": { "a": 0, "k": [0.992156922583, 0.992156922583, 0.992156922583, 1], "ix": 4 },
              "o": { "a": 0, "k": 100, "ix": 5 },
              "r": 1,
              "bm": 0,
              "nm": "Fill 1",
              "mn": "ADBE Vector Graphic - Fill",
              "hd": false
            },
            {
              "ty": "tr",
              "p": { "a": 0, "k": [161.795, 155.474], "ix": 2 },
              "a": { "a": 0, "k": [0, 0], "ix": 1 },
              "s": { "a": 0, "k": [100, 100], "ix": 3 },
              "r": { "a": 0, "k": 0, "ix": 6 },
              "o": { "a": 0, "k": 100, "ix": 7 },
              "sk": { "a": 0, "k": 0, "ix": 4 },
              "sa": { "a": 0, "k": 0, "ix": 5 },
              "nm": "Transform"
            }
          ],
          "nm": "Group 2",
          "np": 2,
          "cix": 2,
          "bm": 0,
          "ix": 2,
          "mn": "ADBE Vector Group",
          "hd": false
        },
        {
          "ty": "gr",
          "it": [
            {
              "ind": 0,
              "ty": "sh",
              "ix": 1,
              "ks": {
                "a": 0,
                "k": {
                  "i": [
                    [0.19, 0],
                    [-0.038, 8.64],
                    [-0.417, 1.577],
                    [-3.261, 0.04],
                    [-0.665, -3.115],
                    [-0.077, -2.477],
                    [-0.45, -16.605],
                    [0.414, -1.92],
                    [3.649, 0.046],
                    [0.646, 3.318],
                    [0.024, 2.642],
                    [0, 8.139]
                  ],
                  "o": [
                    [0, -8.641],
                    [0.007, -1.653],
                    [0.801, -3.025],
                    [3.252, -0.041],
                    [0.512, 2.4],
                    [0.514, 16.603],
                    [0.053, 1.981],
                    [-0.757, 3.512],
                    [-3.427, -0.043],
                    [-0.502, -2.581],
                    [-0.074, -8.138],
                    [-0.19, 0]
                  ],
                  "v": [
                    [-7.368, -0.884],
                    [-7.35, -26.806],
                    [-6.921, -31.75],
                    [-0.828, -36.645],
                    [5.318, -31.906],
                    [5.876, -24.499],
                    [7.335, 25.313],
                    [6.971, 31.256],
                    [0.21, 36.64],
                    [-6.154, 31.443],
                    [-6.771, 23.533],
                    [-7.147, 2.704]
                  ],
                  "c": true
                },
                "ix": 2
              },
              "nm": "Path 1",
              "mn": "ADBE Vector Shape - Group",
              "hd": false
            },
            {
              "ty": "fl",
              "c": { "a": 0, "k": [0.996078491211, 0.996078491211, 0.996078491211, 1], "ix": 4 },
              "o": { "a": 0, "k": 100, "ix": 5 },
              "r": 1,
              "bm": 0,
              "nm": "Fill 1",
              "mn": "ADBE Vector Graphic - Fill",
              "hd": false
            },
            {
              "ty": "tr",
              "p": { "a": 0, "k": [116.077, 151.332], "ix": 2 },
              "a": { "a": 0, "k": [0, 0], "ix": 1 },
              "s": { "a": 0, "k": [100, 100], "ix": 3 },
              "r": { "a": 0, "k": 0, "ix": 6 },
              "o": { "a": 0, "k": 100, "ix": 7 },
              "sk": { "a": 0, "k": 0, "ix": 4 },
              "sa": { "a": 0, "k": 0, "ix": 5 },
              "nm": "Transform"
            }
          ],
          "nm": "Group 3",
          "np": 2,
          "cix": 2,
          "bm": 0,
          "ix": 3,
          "mn": "ADBE Vector Group",
          "hd": false
        },
        {
          "ty": "gr",
          "it": [
            {
              "ind": 0,
              "ty": "sh",
              "ix": 1,
              "ks": {
                "a": 0,
                "k": {
                  "i": [
                    [0, 0],
                    [0.02, 13.122],
                    [-0.901, 1.824],
                    [-3.45, -0.486],
                    [-0.523, -2.918],
                    [0.036, -1.494],
                    [0.671, -25.747],
                    [4.976, 0.118],
                    [-0.034, 7.727],
                    [-0.022, 9.715],
                    [-0.75, 2.866]
                  ],
                  "o": [
                    [0, -13.122],
                    [-0.003, -2.022],
                    [1.509, -3.053],
                    [2.936, 0.414],
                    [0.264, 1.474],
                    [-0.616, 25.747],
                    [-0.204, 7.835],
                    [-4.891, -0.115],
                    [0.048, -11.046],
                    [0.006, -2.962],
                    [0, 0]
                  ],
                  "v": [
                    [-6.776, -3.404],
                    [-6.32, -39.329],
                    [-5.231, -45.153],
                    [2.215, -49.137],
                    [7.958, -43.418],
                    [8.294, -38.924],
                    [6.361, 38.316],
                    [-1.216, 49.506],
                    [-8.296, 37.911],
                    [-8.135, 11.433],
                    [-7.311, 1.107]
                  ],
                  "c": true
                },
                "ix": 2
              },
              "nm": "Path 1",
              "mn": "ADBE Vector Shape - Group",
              "hd": false
            },
            {
              "ty": "fl",
              "c": { "a": 0, "k": [0.996078491211, 0.996078491211, 0.996078491211, 1], "ix": 4 },
              "o": { "a": 0, "k": 100, "ix": 5 },
              "r": 1,
              "bm": 0,
              "nm": "Fill 1",
              "mn": "ADBE Vector Graphic - Fill",
              "hd": false
            },
            {
              "ty": "tr",
              "p": { "a": 0, "k": [212.131, 137.002], "ix": 2 },
              "a": { "a": 0, "k": [0, 0], "ix": 1 },
              "s": { "a": 0, "k": [100, 100], "ix": 3 },
              "r": { "a": 0, "k": 0, "ix": 6 },
              "o": { "a": 0, "k": 100, "ix": 7 },
              "sk": { "a": 0, "k": 0, "ix": 4 },
              "sa": { "a": 0, "k": 0, "ix": 5 },
              "nm": "Transform"
            }
          ],
          "nm": "Group 4",
          "np": 2,
          "cix": 2,
          "bm": 0,
          "ix": 4,
          "mn": "ADBE Vector Group",
          "hd": false
        },
        {
          "ty": "gr",
          "it": [
            {
              "ind": 0,
              "ty": "sh",
              "ix": 1,
              "ks": {
                "a": 0,
                "k": {
                  "i": [
                    [-19.81, 0],
                    [-32.208, 2.874],
                    [-11.312, -0.238],
                    [0.204, -4.163],
                    [4.846, 0.117],
                    [47.295, 1.646],
                    [18.143, -0.724],
                    [0.596, 4.093],
                    [-3.878, 1.106],
                    [-2.66, 0.002]
                  ],
                  "o": [
                    [32.272, -1.16],
                    [11.296, -1.008],
                    [5.112, 0.107],
                    [-0.196, 4.017],
                    [-47.286, -1.139],
                    [-18.131, -0.631],
                    [-3.635, 0.144],
                    [-0.607, -4.17],
                    [2.608, -0.745],
                    [19.81, -0.014]
                  ],
                  "v": [
                    [-32.781, -5.446],
                    [64.005, -9.146],
                    [97.94, -8.617],
                    [106.066, -1.032],
                    [97.79, 5.783],
                    [-43.947, 8.509],
                    [-98.355, 8.196],
                    [-105.663, 2.954],
                    [-100.132, -4.66],
                    [-92.21, -5.438]
                  ],
                  "c": true
                },
                "ix": 2
              },
              "nm": "Path 1",
              "mn": "ADBE Vector Shape - Group",
              "hd": false
            },
            {
              "ty": "fl",
              "c": { "a": 0, "k": [0.996078491211, 0.996078491211, 0.996078491211, 1], "ix": 4 },
              "o": { "a": 0, "k": 100, "ix": 5 },
              "r": 1,
              "bm": 0,
              "nm": "Fill 1",
              "mn": "ADBE Vector Graphic - Fill",
              "hd": false
            },
            {
              "ty": "tr",
              "p": { "a": 0, "k": [115.624, 213.375], "ix": 2 },
              "a": { "a": 0, "k": [0, 0], "ix": 1 },
              "s": { "a": 0, "k": [100, 100], "ix": 3 },
              "r": { "a": 0, "k": 0, "ix": 6 },
              "o": { "a": 0, "k": 100, "ix": 7 },
              "sk": { "a": 0, "k": 0, "ix": 4 },
              "sa": { "a": 0, "k": 0, "ix": 5 },
              "nm": "Transform"
            }
          ],
          "nm": "Group 5",
          "np": 2,
          "cix": 2,
          "bm": 0,
          "ix": 5,
          "mn": "ADBE Vector Group",
          "hd": false
        },
        {
          "ty": "gr",
          "it": [
            {
              "ind": 0,
              "ty": "sh",
              "ix": 1,
              "ks": {
                "a": 0,
                "k": {
                  "i": [
                    [-15.351, 18.965],
                    [5.971, -1.798],
                    [1.253, 3.69],
                    [-4.819, 1.431],
                    [-11.976, -0.597],
                    [-1.539, -4.259],
                    [-2.972, -9.676],
                    [0.315, -1.593],
                    [3.64, -0.255],
                    [0.698, 3.439],
                    [0.73, 6.744],
                    [0.522, -0.719],
                    [10.939, -16.941],
                    [6.542, -3.698],
                    [6.676, 12.142],
                    [11.955, -8.883],
                    [4.571, -6.75],
                    [15.343, -27.302],
                    [3.499, 1.856],
                    [-2.421, 4.598],
                    [-11.188, 16.929],
                    [-11.94, 13.156],
                    [-16.927, -3.705],
                    [-4.547, -9.749],
                    [-6.079, 4.202],
                    [-1.495, 2.109]
                  ],
                  "o": [
                    [-7.655, 0.052],
                    [-5.128, 1.543],
                    [-1.293, -3.807],
                    [11.622, -3.451],
                    [5.061, 0.252],
                    [3.438, 9.515],
                    [0.466, 1.518],
                    [-0.678, 3.423],
                    [-3.64, 0.255],
                    [-1.364, -6.717],
                    [-1.573, -0.502],
                    [-11.813, 16.289],
                    [-4.006, 6.205],
                    [-12.07, 6.823],
                    [-7.029, -12.783],
                    [-6.617, 4.917],
                    [-17.53, 25.887],
                    [-2.659, 4.732],
                    [-3.407, -1.808],
                    [9.463, -17.965],
                    [9.714, -14.7],
                    [11.937, -13.153],
                    [10.069, 2.205],
                    [3.121, 6.694],
                    [2.169, -1.499],
                    [13.255, -18.704]
                  ],
                  "v": [
                    [79.838, -73.827],
                    [60.124, -72.068],
                    [50.539, -75.43],
                    [56.096, -84.524],
                    [91.699, -87.621],
                    [101.19, -79.002],
                    [110.525, -50.108],
                    [110.568, -45.166],
                    [104.172, -39.182],
                    [97.115, -44.241],
                    [91.463, -63.723],
                    [89.027, -62.305],
                    [53.26, -13.675],
                    [37.6, 1.447],
                    [7.124, -7.147],
                    [-29.724, -14.856],
                    [-46.134, 3.164],
                    [-97.008, 81.943],
                    [-106.65, 86.362],
                    [-108.57, 75.871],
                    [-77.321, 23.674],
                    [-46.652, -19.368],
                    [-3.191, -32.751],
                    [19.315, -15.56],
                    [31.862, -12.31],
                    [37.791, -17.593]
                  ],
                  "c": true
                },
                "ix": 2
              },
              "nm": "Path 1",
              "mn": "ADBE Vector Shape - Group",
              "hd": false
            },
            {
              "ty": "fl",
              "c": { "a": 0, "k": [0.996078491211, 0.996078491211, 0.996078491211, 1], "ix": 4 },
              "o": { "a": 0, "k": 100, "ix": 5 },
              "r": 1,
              "bm": 0,
              "nm": "Fill 1",
              "mn": "ADBE Vector Graphic - Fill",
              "hd": false
            },
            {
              "ty": "tr",
              "p": { "a": 0, "k": [125.291, 111.636], "ix": 2 },
              "a": { "a": 0, "k": [0, 0], "ix": 1 },
              "s": { "a": 0, "k": [100, 100], "ix": 3 },
              "r": { "a": 0, "k": 0, "ix": 6 },
              "o": { "a": 0, "k": 100, "ix": 7 },
              "sk": { "a": 0, "k": 0, "ix": 4 },
              "sa": { "a": 0, "k": 0, "ix": 5 },
              "nm": "Transform"
            }
          ],
          "nm": "Group 6",
          "np": 2,
          "cix": 2,
          "bm": 0,
          "ix": 6,
          "mn": "ADBE Vector Group",
          "hd": false
        }
      ],
      "ip": 8.00000032584668,
      "op": 12.00000048877,
      "st": 0,
      "ct": 1,
      "bm": 0
    },
    {
      "ddd": 0,
      "ind": 2,
      "ty": 4,
      "nm": "Layer 2 Outlines",
      "sr": 1,
      "ks": {
        "o": { "a": 0, "k": 100, "ix": 11 },
        "r": { "a": 0, "k": 0, "ix": 10 },
        "p": { "s": true, "x": { "a": 0, "k": 120, "ix": 3 }, "y": { "a": 0, "k": 120, "ix": 4 } },
        "a": { "a": 0, "k": [120, 120, 0], "ix": 1, "l": 2 },
        "s": { "a": 0, "k": [100, 100, 100], "ix": 6, "l": 2 }
      },
      "ao": 0,
      "shapes": [
        {
          "ty": "gr",
          "it": [
            {
              "ind": 0,
              "ty": "sh",
              "ix": 1,
              "ks": {
                "a": 0,
                "k": {
                  "i": [
                    [-1.182, -7.211],
                    [4.192, -0.378],
                    [0.715, 5.48],
                    [0.643, 5.782],
                    [-0.959, 1.34],
                    [-2.436, 0.553],
                    [-0.593, -3.374]
                  ],
                  "o": [
                    [-0.158, 5.658],
                    [-4.287, 0.388],
                    [-0.752, -5.77],
                    [-0.216, -1.943],
                    [1.557, -2.174],
                    [3.226, -0.734],
                    [1.266, 7.195]
                  ],
                  "v": [
                    [8.544, 8.928],
                    [2.027, 18.202],
                    [-5.657, 10.351],
                    [-7.917, -6.957],
                    [-7.585, -12.76],
                    [-1.194, -17.856],
                    [4.971, -12.699]
                  ],
                  "c": true
                },
                "ix": 2
              },
              "nm": "Path 1",
              "mn": "ADBE Vector Shape - Group",
              "hd": false
            },
            {
              "ty": "fl",
              "c": { "a": 0, "k": [1, 1, 1, 1], "ix": 4 },
              "o": { "a": 0, "k": 100, "ix": 5 },
              "r": 1,
              "bm": 0,
              "nm": "Fill 1",
              "mn": "ADBE Vector Graphic - Fill",
              "hd": false
            },
            {
              "ty": "tr",
              "p": { "a": 0, "k": [72.264, 172.231], "ix": 2 },
              "a": { "a": 0, "k": [0, 0], "ix": 1 },
              "s": { "a": 0, "k": [100, 100], "ix": 3 },
              "r": { "a": 0, "k": 0, "ix": 6 },
              "o": { "a": 0, "k": 100, "ix": 7 },
              "sk": { "a": 0, "k": 0, "ix": 4 },
              "sa": { "a": 0, "k": 0, "ix": 5 },
              "nm": "Transform"
            }
          ],
          "nm": "Group 1",
          "np": 2,
          "cix": 2,
          "bm": 0,
          "ix": 1,
          "mn": "ADBE Vector Group",
          "hd": false
        },
        {
          "ty": "gr",
          "it": [
            {
              "ind": 0,
              "ty": "sh",
              "ix": 1,
              "ks": {
                "a": 0,
                "k": {
                  "i": [
                    [-0.482, -5.651],
                    [5.072, -0.003],
                    [0.321, 7.491],
                    [0.489, 9.291],
                    [-0.31, 1.94],
                    [-3.963, 0.002],
                    [-0.488, -3.531],
                    [-0.367, -4.299]
                  ],
                  "o": [
                    [0.289, 9.12],
                    [-4.845, 0.004],
                    [-0.398, -9.295],
                    [-0.105, -1.984],
                    [0.584, -3.658],
                    [3.692, -0.002],
                    [0.59, 4.268],
                    [0.593, 6.952]
                  ],
                  "v": [
                    [7.925, 12.745],
                    [0.918, 25.473],
                    [-6.424, 14.553],
                    [-7.95, -13.317],
                    [-7.904, -19.275],
                    [-1.293, -25.475],
                    [5.103, -19.699],
                    [6.258, -6.81]
                  ],
                  "c": true
                },
                "ix": 2
              },
              "nm": "Path 1",
              "mn": "ADBE Vector Shape - Group",
              "hd": false
            },
            {
              "ty": "fl",
              "c": { "a": 0, "k": [1, 1, 1, 1], "ix": 4 },
              "o": { "a": 0, "k": 100, "ix": 5 },
              "r": 1,
              "bm": 0,
              "nm": "Fill 1",
              "mn": "ADBE Vector Graphic - Fill",
              "hd": false
            },
            {
              "ty": "tr",
              "p": { "a": 0, "k": [163.251, 153.79], "ix": 2 },
              "a": { "a": 0, "k": [0, 0], "ix": 1 },
              "s": { "a": 0, "k": [100, 100], "ix": 3 },
              "r": { "a": 0, "k": 0, "ix": 6 },
              "o": { "a": 0, "k": 100, "ix": 7 },
              "sk": { "a": 0, "k": 0, "ix": 4 },
              "sa": { "a": 0, "k": 0, "ix": 5 },
              "nm": "Transform"
            }
          ],
          "nm": "Group 2",
          "np": 2,
          "cix": 2,
          "bm": 0,
          "ix": 2,
          "mn": "ADBE Vector Group",
          "hd": false
        },
        {
          "ty": "gr",
          "it": [
            {
              "ind": 0,
              "ty": "sh",
              "ix": 1,
              "ks": {
                "a": 0,
                "k": {
                  "i": [
                    [0.36, 0.001],
                    [-0.091, 8.826],
                    [-4.201, 0.127],
                    [-0.29, -5.995],
                    [-0.982, -18.78],
                    [4.361, -0.924],
                    [1.322, 4.163],
                    [0.039, 2.462],
                    [0, 8.485]
                  ],
                  "o": [
                    [0, -8.826],
                    [0.059, -5.743],
                    [4.392, -0.132],
                    [0.909, 18.783],
                    [0.216, 4.147],
                    [-4.487, 0.952],
                    [-0.743, -2.339],
                    [-0.134, -8.483],
                    [-0.36, -0.002]
                  ],
                  "v": [
                    [-8.322, -1.854],
                    [-8.299, -28.333],
                    [-1.695, -37.199],
                    [5.314, -28.231],
                    [8.174, 28.113],
                    [2.734, 36.379],
                    [-6.055, 30.952],
                    [-7.191, 23.604],
                    [-7.708, 4.268]
                  ],
                  "c": true
                },
                "ix": 2
              },
              "nm": "Path 1",
              "mn": "ADBE Vector Shape - Group",
              "hd": false
            },
            {
              "ty": "fl",
              "c": { "a": 0, "k": [1, 1, 1, 1], "ix": 4 },
              "o": { "a": 0, "k": 100, "ix": 5 },
              "r": 1,
              "bm": 0,
              "nm": "Fill 1",
              "mn": "ADBE Vector Graphic - Fill",
              "hd": false
            },
            {
              "ty": "tr",
              "p": { "a": 0, "k": [116.977, 151.84], "ix": 2 },
              "a": { "a": 0, "k": [0, 0], "ix": 1 },
              "s": { "a": 0, "k": [100, 100], "ix": 3 },
              "r": { "a": 0, "k": 0, "ix": 6 },
              "o": { "a": 0, "k": 100, "ix": 7 },
              "sk": { "a": 0, "k": 0, "ix": 4 },
              "sa": { "a": 0, "k": 0, "ix": 5 },
              "nm": "Transform"
            }
          ],
          "nm": "Group 3",
          "np": 2,
          "cix": 2,
          "bm": 0,
          "ix": 3,
          "mn": "ADBE Vector Group",
          "hd": false
        },
        {
          "ty": "gr",
          "it": [
            {
              "ind": 0,
              "ty": "sh",
              "ix": 1,
              "ks": {
                "a": 0,
                "k": {
                  "i": [
                    [0.124, 0],
                    [0.016, -13.139],
                    [4.537, -0.212],
                    [0.021, 6.138],
                    [-0.248, 11.474],
                    [-0.368, 13.968],
                    [-0.112, 1.158],
                    [-4.114, -0.259],
                    [-0.015, -5.581],
                    [0, -13.14]
                  ],
                  "o": [
                    [0, 13.139],
                    [-0.007, 5.985],
                    [-4.635, 0.217],
                    [-0.038, -11.475],
                    [0.303, -13.97],
                    [0.031, -1.164],
                    [0.551, -5.656],
                    [4.029, 0.254],
                    [0.034, 13.139],
                    [-0.125, -0.001]
                  ],
                  "v": [
                    [7.546, 2.365],
                    [7.337, 39.177],
                    [0.224, 48.821],
                    [-7.7, 39.384],
                    [-7.207, 4.957],
                    [-6.134, -36.948],
                    [-5.937, -40.436],
                    [1.293, -48.778],
                    [7.705, -39.657],
                    [7.716, -0.238]
                  ],
                  "c": true
                },
                "ix": 2
              },
              "nm": "Path 1",
              "mn": "ADBE Vector Shape - Group",
              "hd": false
            },
            {
              "ty": "fl",
              "c": { "a": 0, "k": [1, 1, 1, 1], "ix": 4 },
              "o": { "a": 0, "k": 100, "ix": 5 },
              "r": 1,
              "bm": 0,
              "nm": "Fill 1",
              "mn": "ADBE Vector Graphic - Fill",
              "hd": false
            },
            {
              "ty": "tr",
              "p": { "a": 0, "k": [212.351, 134.999], "ix": 2 },
              "a": { "a": 0, "k": [0, 0], "ix": 1 },
              "s": { "a": 0, "k": [100, 100], "ix": 3 },
              "r": { "a": 0, "k": 0, "ix": 6 },
              "o": { "a": 0, "k": 100, "ix": 7 },
              "sk": { "a": 0, "k": 0, "ix": 4 },
              "sa": { "a": 0, "k": 0, "ix": 5 },
              "nm": "Transform"
            }
          ],
          "nm": "Group 4",
          "np": 2,
          "cix": 2,
          "bm": 0,
          "ix": 4,
          "mn": "ADBE Vector Group",
          "hd": false
        },
        {
          "ty": "gr",
          "it": [
            {
              "ind": 0,
              "ty": "sh",
              "ix": 1,
              "ks": {
                "a": 0,
                "k": {
                  "i": [
                    [0.024, 0.178],
                    [20.434, -0.792],
                    [10.142, -0.007],
                    [15.318, -0.023],
                    [6.32, 0.244],
                    [-0.167, 4.07],
                    [-4.832, 0.062],
                    [-24.954, 0.545],
                    [-12.801, 0.375],
                    [-13.978, 0.142],
                    [-12.648, 0.252],
                    [-0.832, 0.009],
                    [-0.276, -4.576],
                    [6.244, -0.122],
                    [13.148, 0]
                  ],
                  "o": [
                    [-20.424, 1.065],
                    [-10.124, 0.392],
                    [-15.318, 0.011],
                    [-6.325, 0.009],
                    [-5.248, -0.202],
                    [0.156, -3.82],
                    [24.959, -0.324],
                    [12.8, -0.28],
                    [13.968, -0.408],
                    [12.649, -0.128],
                    [0.833, -0.017],
                    [6.067, -0.067],
                    [0.29, 4.783],
                    [-13.143, 0.258],
                    [-0.024, -0.178]
                  ],
                  "v": [
                    [57.883, 5.626],
                    [-3.391, 8.74],
                    [-33.814, 8.607],
                    [-79.768, 8.791],
                    [-98.743, 8.51],
                    [-106.727, 1.542],
                    [-98.758, -5.031],
                    [-23.881, -5.891],
                    [14.492, -8.059],
                    [56.426, -8.258],
                    [94.37, -8.982],
                    [96.867, -9.066],
                    [106.604, -2.14],
                    [97.397, 6.082],
                    [57.954, 6.16]
                  ],
                  "c": true
                },
                "ix": 2
              },
              "nm": "Path 1",
              "mn": "ADBE Vector Shape - Group",
              "hd": false
            },
            {
              "ty": "fl",
              "c": { "a": 0, "k": [1, 1, 1, 1], "ix": 4 },
              "o": { "a": 0, "k": 100, "ix": 5 },
              "r": 1,
              "bm": 0,
              "nm": "Fill 1",
              "mn": "ADBE Vector Graphic - Fill",
              "hd": false
            },
            {
              "ty": "tr",
              "p": { "a": 0, "k": [115.738, 212.903], "ix": 2 },
              "a": { "a": 0, "k": [0, 0], "ix": 1 },
              "s": { "a": 0, "k": [100, 100], "ix": 3 },
              "r": { "a": 0, "k": 0, "ix": 6 },
              "o": { "a": 0, "k": 100, "ix": 7 },
              "sk": { "a": 0, "k": 0, "ix": 4 },
              "sa": { "a": 0, "k": 0, "ix": 5 },
              "nm": "Transform"
            }
          ],
          "nm": "Group 5",
          "np": 2,
          "cix": 2,
          "bm": 0,
          "ix": 5,
          "mn": "ADBE Vector Group",
          "hd": false
        },
        {
          "ty": "gr",
          "it": [
            {
              "ind": 0,
              "ty": "sh",
              "ix": 1,
              "ks": {
                "a": 0,
                "k": {
                  "i": [
                    [-6.592, 9.47],
                    [5.967, -1.333],
                    [1.374, 3.794],
                    [-4.947, 0.883],
                    [-12.678, 0.33],
                    [-2.031, -7.625],
                    [-1.596, -8.337],
                    [0.301, -1.262],
                    [4.367, 0.126],
                    [0.55, 4.211],
                    [1.12, 7.161],
                    [0.462, 0.101],
                    [4.972, -6.409],
                    [10.902, -13.219],
                    [4.291, -2.376],
                    [7.109, 7.212],
                    [5.854, 4.268],
                    [3.931, -3.16],
                    [5.425, -7.091],
                    [12.656, -18.356],
                    [5.872, -9.255],
                    [3.376, 1.265],
                    [-0.803, 3.356],
                    [-1.869, 2.869],
                    [-15.238, 22.036],
                    [-6.906, 7.66],
                    [-2.067, 1.365],
                    [-21.529, -15.681],
                    [-2.203, -2.485],
                    [-4.274, 3.866],
                    [-3.832, 4.582],
                    [-5.647, 7.621]
                  ],
                  "o": [
                    [-7.284, 1.271],
                    [-5.295, 1.183],
                    [-1.343, -3.709],
                    [12.536, -2.239],
                    [8.386, -0.218],
                    [2.18, 8.186],
                    [0.244, 1.275],
                    [-1.018, 4.273],
                    [-4.398, -0.126],
                    [-0.939, -7.185],
                    [-0.461, -0.1],
                    [-4.818, 6.529],
                    [-10.505, 13.542],
                    [-3.098, 3.756],
                    [-8.896, 4.928],
                    [-5.046, -5.12],
                    [-4.232, -3.086],
                    [-7.079, 5.691],
                    [-13.539, 17.695],
                    [-6.217, 9.017],
                    [-1.959, 3.088],
                    [-3.423, -1.283],
                    [0.8, -3.345],
                    [14.623, -22.456],
                    [5.825, -8.425],
                    [1.659, -1.84],
                    [18.407, -12.16],
                    [2.652, 1.931],
                    [3.818, 4.304],
                    [4.424, -4.001],
                    [6.085, -7.279],
                    [5.92, -7.988]
                  ],
                  "v": [
                    [77.589, -74.268],
                    [58.261, -70.828],
                    [48.158, -74.413],
                    [53.603, -83.511],
                    [91.509, -88.27],
                    [106.49, -73.58],
                    [111.576, -48.636],
                    [111.488, -44.672],
                    [103.252, -38.137],
                    [96.461, -45.305],
                    [93.15, -66.795],
                    [91.766, -67.096],
                    [77.285, -47.53],
                    [45.417, -7.184],
                    [33.81, 2.109],
                    [7.988, -2.892],
                    [-9.065, -16.348],
                    [-22.124, -16.212],
                    [-42.368, 1.985],
                    [-81.096, 56.511],
                    [-98.783, 84.227],
                    [-106.936, 87.223],
                    [-111.016, 79.544],
                    [-107.061, 69.911],
                    [-62.706, 2.866],
                    [-42.362, -20.417],
                    [-36.695, -25.3],
                    [11.535, -21.307],
                    [18.553, -14.236],
                    [29.561, -13.175],
                    [41.901, -26.197],
                    [59.579, -48.511]
                  ],
                  "c": true
                },
                "ix": 2
              },
              "nm": "Path 1",
              "mn": "ADBE Vector Shape - Group",
              "hd": false
            },
            {
              "ty": "fl",
              "c": { "a": 0, "k": [1, 1, 1, 1], "ix": 4 },
              "o": { "a": 0, "k": 100, "ix": 5 },
              "r": 1,
              "bm": 0,
              "nm": "Fill 1",
              "mn": "ADBE Vector Graphic - Fill",
              "hd": false
            },
            {
              "ty": "tr",
              "p": { "a": 0, "k": [125.334, 111.472], "ix": 2 },
              "a": { "a": 0, "k": [0, 0], "ix": 1 },
              "s": { "a": 0, "k": [100, 100], "ix": 3 },
              "r": { "a": 0, "k": 0, "ix": 6 },
              "o": { "a": 0, "k": 100, "ix": 7 },
              "sk": { "a": 0, "k": 0, "ix": 4 },
              "sa": { "a": 0, "k": 0, "ix": 5 },
              "nm": "Transform"
            }
          ],
          "nm": "Group 6",
          "np": 2,
          "cix": 2,
          "bm": 0,
          "ix": 6,
          "mn": "ADBE Vector Group",
          "hd": false
        }
      ],
      "ip": 4.00000016292334,
      "op": 8.00000032584668,
      "st": 0,
      "ct": 1,
      "bm": 0
    },
    {
      "ddd": 0,
      "ind": 3,
      "ty": 4,
      "nm": "Layer 1 Outlines",
      "sr": 1,
      "ks": {
        "o": { "a": 0, "k": 100, "ix": 11 },
        "r": { "a": 0, "k": 0, "ix": 10 },
        "p": { "s": true, "x": { "a": 0, "k": 120, "ix": 3 }, "y": { "a": 0, "k": 120, "ix": 4 } },
        "a": { "a": 0, "k": [120, 120, 0], "ix": 1, "l": 2 },
        "s": { "a": 0, "k": [100, 100, 100], "ix": 6, "l": 2 }
      },
      "ao": 0,
      "shapes": [
        {
          "ty": "gr",
          "it": [
            {
              "ind": 0,
              "ty": "sh",
              "ix": 1,
              "ks": {
                "a": 0,
                "k": {
                  "i": [
                    [-0.732, -4.543],
                    [3.835, -0.343],
                    [0.782, 4.677],
                    [0.992, 6.915],
                    [-4.124, 1.077],
                    [-1.475, -3.88],
                    [-0.278, -1.632]
                  ],
                  "o": [
                    [0.047, 6.092],
                    [-3.845, 0.344],
                    [-1.153, -6.89],
                    [-0.551, -3.844],
                    [4.289, -1.121],
                    [0.587, 1.545],
                    [1.007, 5.901]
                  ],
                  "v": [
                    [8.772, 8.673],
                    [2.551, 18.333],
                    [-5.044, 11.383],
                    [-8.268, -9.325],
                    [-3.637, -17.555],
                    [4.847, -12.506],
                    [6.114, -7.688]
                  ],
                  "c": true
                },
                "ix": 2
              },
              "nm": "Path 1",
              "mn": "ADBE Vector Shape - Group",
              "hd": false
            },
            {
              "ty": "fl",
              "c": { "a": 0, "k": [1, 1, 1, 1], "ix": 4 },
              "o": { "a": 0, "k": 100, "ix": 5 },
              "r": 1,
              "bm": 0,
              "nm": "Fill 1",
              "mn": "ADBE Vector Graphic - Fill",
              "hd": false
            },
            {
              "ty": "tr",
              "p": { "a": 0, "k": [72.809, 172.561], "ix": 2 },
              "a": { "a": 0, "k": [0, 0], "ix": 1 },
              "s": { "a": 0, "k": [100, 100], "ix": 3 },
              "r": { "a": 0, "k": 0, "ix": 6 },
              "o": { "a": 0, "k": 100, "ix": 7 },
              "sk": { "a": 0, "k": 0, "ix": 4 },
              "sa": { "a": 0, "k": 0, "ix": 5 },
              "nm": "Transform"
            }
          ],
          "nm": "Group 1",
          "np": 2,
          "cix": 2,
          "bm": 0,
          "ix": 1,
          "mn": "ADBE Vector Group",
          "hd": false
        },
        {
          "ty": "gr",
          "it": [
            {
              "ind": 0,
              "ty": "sh",
              "ix": 1,
              "ks": {
                "a": 0,
                "k": {
                  "i": [
                    [-0.56, -13.131],
                    [4.367, -0.607],
                    [0.714, 3.993],
                    [0.227, 5.478],
                    [0.003, 8.161],
                    [-1.035, 1.151],
                    [-1.972, -0.091],
                    [-1.551, -1.713],
                    [-0.069, -1.476]
                  ],
                  "o": [
                    [0.562, 4.123],
                    [-4.403, 0.611],
                    [-0.963, -5.387],
                    [-0.338, -8.151],
                    [0, -1.781],
                    [1.509, -1.677],
                    [1.967, 0.09],
                    [0.868, 0.959],
                    [0.616, 13.128]
                  ],
                  "v": [
                    [7.412, 19.677],
                    [1.935, 27.474],
                    [-5.978, 21.542],
                    [-7.622, 5.164],
                    [-7.974, -19.316],
                    [-6.884, -24.539],
                    [-0.936, -27.994],
                    [4.7, -24.019],
                    [5.7, -19.715]
                  ],
                  "c": true
                },
                "ix": 2
              },
              "nm": "Path 1",
              "mn": "ADBE Vector Shape - Group",
              "hd": false
            },
            {
              "ty": "fl",
              "c": { "a": 0, "k": [1, 1, 1, 1], "ix": 4 },
              "o": { "a": 0, "k": 100, "ix": 5 },
              "r": 1,
              "bm": 0,
              "nm": "Fill 1",
              "mn": "ADBE Vector Graphic - Fill",
              "hd": false
            },
            {
              "ty": "tr",
              "p": { "a": 0, "k": [163.097, 155.469], "ix": 2 },
              "a": { "a": 0, "k": [0, 0], "ix": 1 },
              "s": { "a": 0, "k": [100, 100], "ix": 3 },
              "r": { "a": 0, "k": 0, "ix": 6 },
              "o": { "a": 0, "k": 100, "ix": 7 },
              "sk": { "a": 0, "k": 0, "ix": 4 },
              "sa": { "a": 0, "k": 0, "ix": 5 },
              "nm": "Transform"
            }
          ],
          "nm": "Group 2",
          "np": 2,
          "cix": 2,
          "bm": 0,
          "ix": 2,
          "mn": "ADBE Vector Group",
          "hd": false
        },
        {
          "ty": "gr",
          "it": [
            {
              "ind": 0,
              "ty": "sh",
              "ix": 1,
              "ks": {
                "a": 0,
                "k": {
                  "i": [
                    [0.209, -0.024],
                    [-1.15, -11.903],
                    [4.408, -0.643],
                    [0.237, 6.185],
                    [0.319, 18.771],
                    [-4.628, 0.204],
                    [-0.192, -4.815],
                    [0, -6.157]
                  ],
                  "o": [
                    [1.032, 11.914],
                    [0.571, 5.905],
                    [-4.788, 0.699],
                    [-0.719, -18.758],
                    [-0.07, -4.073],
                    [3.951, -0.174],
                    [0.246, 6.147],
                    [-0.21, 0.023]
                  ],
                  "v": [
                    [5.257, -6.08],
                    [7.738, 25.383],
                    [1.885, 35.835],
                    [-6.857, 27.285],
                    [-8.239, -29.018],
                    [-1.811, -36.359],
                    [5.175, -28.895],
                    [5.235, -10.426]
                  ],
                  "c": true
                },
                "ix": 2
              },
              "nm": "Path 1",
              "mn": "ADBE Vector Shape - Group",
              "hd": false
            },
            {
              "ty": "fl",
              "c": { "a": 0, "k": [1, 1, 1, 1], "ix": 4 },
              "o": { "a": 0, "k": 100, "ix": 5 },
              "r": 1,
              "bm": 0,
              "nm": "Fill 1",
              "mn": "ADBE Vector Graphic - Fill",
              "hd": false
            },
            {
              "ty": "tr",
              "p": { "a": 0, "k": [116.822, 151.197], "ix": 2 },
              "a": { "a": 0, "k": [0, 0], "ix": 1 },
              "s": { "a": 0, "k": [100, 100], "ix": 3 },
              "r": { "a": 0, "k": 0, "ix": 6 },
              "o": { "a": 0, "k": 100, "ix": 7 },
              "sk": { "a": 0, "k": 0, "ix": 4 },
              "sa": { "a": 0, "k": 0, "ix": 5 },
              "nm": "Transform"
            }
          ],
          "nm": "Group 3",
          "np": 2,
          "cix": 2,
          "bm": 0,
          "ix": 3,
          "mn": "ADBE Vector Group",
          "hd": false
        },
        {
          "ty": "gr",
          "it": [
            {
              "ind": 0,
              "ty": "sh",
              "ix": 1,
              "ks": {
                "a": 0,
                "k": {
                  "i": [
                    [-0.018, 0],
                    [0.01, -12.974],
                    [0.209, -1.303],
                    [3.779, -0.39],
                    [1.135, 3.589],
                    [-0.03, 2.125],
                    [-0.353, 15.97],
                    [-0.271, 9.148],
                    [-0.232, 1.301],
                    [-4.393, -0.267],
                    [0.024, -4.203],
                    [0.043, -10.152],
                    [0, -3.328]
                  ],
                  "o": [
                    [0, 12.974],
                    [-0.002, 1.329],
                    [-0.595, 3.711],
                    [-3.808, 0.393],
                    [-0.642, -2.029],
                    [0.226, -15.972],
                    [0.202, -9.149],
                    [0.04, -1.329],
                    [0.727, -4.078],
                    [4.513, 0.274],
                    [-0.057, 10.153],
                    [-0.015, 3.328],
                    [0.018, 0]
                  ],
                  "v": [
                    [7.601, -0.715],
                    [7.594, 38.208],
                    [7.426, 42.19],
                    [0.887, 48.644],
                    [-6.714, 43.565],
                    [-7.691, 37.193],
                    [-6.785, -10.719],
                    [-6.009, -38.164],
                    [-5.743, -42.143],
                    [1.6, -48.77],
                    [7.697, -41.157],
                    [7.551, -10.7],
                    [7.548, -0.715]
                  ],
                  "c": true
                },
                "ix": 2
              },
              "nm": "Path 1",
              "mn": "ADBE Vector Shape - Group",
              "hd": false
            },
            {
              "ty": "fl",
              "c": { "a": 0, "k": [1, 1, 1, 1], "ix": 4 },
              "o": { "a": 0, "k": 100, "ix": 5 },
              "r": 1,
              "bm": 0,
              "nm": "Fill 1",
              "mn": "ADBE Vector Graphic - Fill",
              "hd": false
            },
            {
              "ty": "tr",
              "p": { "a": 0, "k": [212.641, 136.278], "ix": 2 },
              "a": { "a": 0, "k": [0, 0], "ix": 1 },
              "s": { "a": 0, "k": [100, 100], "ix": 3 },
              "r": { "a": 0, "k": 0, "ix": 6 },
              "o": { "a": 0, "k": 100, "ix": 7 },
              "sk": { "a": 0, "k": 0, "ix": 4 },
              "sa": { "a": 0, "k": 0, "ix": 5 },
              "nm": "Transform"
            }
          ],
          "nm": "Group 4",
          "np": 2,
          "cix": 2,
          "bm": 0,
          "ix": 4,
          "mn": "ADBE Vector Group",
          "hd": false
        },
        {
          "ty": "gr",
          "it": [
            {
              "ind": 0,
              "ty": "sh",
              "ix": 1,
              "ks": {
                "a": 0,
                "k": {
                  "i": [
                    [0, -0.015],
                    [25.292, -0.059],
                    [16.96, -0.079],
                    [1.345, 1.002],
                    [-0.32, 1.731],
                    [-2.135, 0.437],
                    [-6.461, 0.07],
                    [-49.25, 0.391],
                    [-9.99, -0.05],
                    [-1.774, -0.382],
                    [0.548, -4.284],
                    [5.102, 0],
                    [23.136, 0]
                  ],
                  "o": [
                    [-25.292, 0],
                    [-16.96, 0.04],
                    [-1.969, 0.01],
                    [-1.886, -1.404],
                    [0.44, -2.373],
                    [6.303, -1.292],
                    [49.248, -0.536],
                    [9.989, -0.079],
                    [1.821, 0.01],
                    [5.056, 1.088],
                    [-0.519, 4.052],
                    [-23.136, -0.002],
                    [0, 0.014]
                  ],
                  "v": [
                    [29.08, 7.445],
                    [-46.796, 7.46],
                    [-97.676, 7.782],
                    [-103.465, 7.153],
                    [-107.465, 1.229],
                    [-102.381, -4.935],
                    [-83.066, -6.77],
                    [64.682, -8.076],
                    [94.652, -8.055],
                    [100.107, -7.547],
                    [107.238, 1.104],
                    [98.489, 7.402],
                    [29.081, 7.401]
                  ],
                  "c": true
                },
                "ix": 2
              },
              "nm": "Path 1",
              "mn": "ADBE Vector Shape - Group",
              "hd": false
            },
            {
              "ty": "fl",
              "c": { "a": 0, "k": [1, 1, 1, 1], "ix": 4 },
              "o": { "a": 0, "k": 100, "ix": 5 },
              "r": 1,
              "bm": 0,
              "nm": "Fill 1",
              "mn": "ADBE Vector Graphic - Fill",
              "hd": false
            },
            {
              "ty": "tr",
              "p": { "a": 0, "k": [113.818, 212.92], "ix": 2 },
              "a": { "a": 0, "k": [0, 0], "ix": 1 },
              "s": { "a": 0, "k": [100, 100], "ix": 3 },
              "r": { "a": 0, "k": 0, "ix": 6 },
              "o": { "a": 0, "k": 100, "ix": 7 },
              "sk": { "a": 0, "k": 0, "ix": 4 },
              "sa": { "a": 0, "k": 0, "ix": 5 },
              "nm": "Transform"
            }
          ],
          "nm": "Group 5",
          "np": 2,
          "cix": 2,
          "bm": 0,
          "ix": 5,
          "mn": "ADBE Vector Group",
          "hd": false
        },
        {
          "ty": "gr",
          "it": [
            {
              "ind": 0,
              "ty": "sh",
              "ix": 1,
              "ks": {
                "a": 0,
                "k": {
                  "i": [
                    [-0.702, 1.457],
                    [7.961, -1.389],
                    [0.848, 4.329],
                    [-4.297, 0.602],
                    [-9.742, 1.209],
                    [-1.991, -0.082],
                    [-3.052, -11.529],
                    [-1.457, -8.021],
                    [4.404, -0.814],
                    [1.135, 6.024],
                    [1.517, 7.833],
                    [5.484, -6.389],
                    [10.279, -10.874],
                    [3.702, -2.204],
                    [9.912, 8.712],
                    [0.93, 0.702],
                    [13.432, -13.017],
                    [5.62, -7.625],
                    [13.253, -18.571],
                    [2.295, -4.045],
                    [4.01, 1.736],
                    [-1.88, 3.668],
                    [-3.865, 5.588],
                    [-15.088, 20.734],
                    [-13.395, 5.413],
                    [-10.288, -6.778],
                    [-3.399, -2.659],
                    [-3.581, 2.654],
                    [-5.644, 6.324],
                    [-10.067, 12.622]
                  ],
                  "o": [
                    [-8.733, 1.371],
                    [-4.559, 0.794],
                    [-0.738, -3.763],
                    [9.722, -1.362],
                    [1.975, -0.245],
                    [11.905, 0.493],
                    [2.084, 7.874],
                    [1.057, 5.826],
                    [-4.817, 0.889],
                    [-1.283, -6.812],
                    [-5.617, 7.536],
                    [-9.746, 11.353],
                    [-2.906, 3.074],
                    [-10.866, 6.47],
                    [-0.87, -0.765],
                    [-14.195, -10.736],
                    [-6.769, 6.56],
                    [-13.536, 18.365],
                    [-2.7, 3.782],
                    [-2.116, 3.731],
                    [-4.055, -1.756],
                    [3.099, -6.046],
                    [14.587, -21.092],
                    [8.156, -11.209],
                    [11.287, -4.56],
                    [3.614, 2.382],
                    [3.633, 2.842],
                    [6.9, -5.114],
                    [10.735, -12.028],
                    [0.38, -0.476]
                  ],
                  "v": [
                    [79.329, -74.709],
                    [54.633, -70.793],
                    [45.251, -76.64],
                    [51.887, -85.128],
                    [81.09, -88.934],
                    [87.079, -89.12],
                    [107.882, -72.721],
                    [112.939, -48.788],
                    [107.243, -38.2],
                    [97.947, -46.275],
                    [93.801, -67.721],
                    [78.018, -46.717],
                    [47.913, -13.411],
                    [37.355, -5.949],
                    [6.025, -8.06],
                    [3.163, -10.068],
                    [-34.226, -5.598],
                    [-52.376, 16.288],
                    [-92.388, 71.821],
                    [-99.798, 83.654],
                    [-108.868, 87.467],
                    [-112.117, 78.247],
                    [-101.672, 60.708],
                    [-57.448, -2.248],
                    [-26.532, -29.122],
                    [5.853, -26.326],
                    [16.626, -19.084],
                    [27.646, -18.26],
                    [47.641, -34.47],
                    [78.07, -72.137]
                  ],
                  "c": true
                },
                "ix": 2
              },
              "nm": "Path 1",
              "mn": "ADBE Vector Shape - Group",
              "hd": false
            },
            {
              "ty": "fl",
              "c": { "a": 0, "k": [1, 1, 1, 1], "ix": 4 },
              "o": { "a": 0, "k": 100, "ix": 5 },
              "r": 1,
              "bm": 0,
              "nm": "Fill 1",
              "mn": "ADBE Vector Graphic - Fill",
              "hd": false
            },
            {
              "ty": "tr",
              "p": { "a": 0, "k": [125.908, 112.388], "ix": 2 },
              "a": { "a": 0, "k": [0, 0], "ix": 1 },
              "s": { "a": 0, "k": [100, 100], "ix": 3 },
              "r": { "a": 0, "k": 0, "ix": 6 },
              "o": { "a": 0, "k": 100, "ix": 7 },
              "sk": { "a": 0, "k": 0, "ix": 4 },
              "sa": { "a": 0, "k": 0, "ix": 5 },
              "nm": "Transform"
            }
          ],
          "nm": "Group 6",
          "np": 2,
          "cix": 2,
          "bm": 0,
          "ix": 6,
          "mn": "ADBE Vector Group",
          "hd": false
        }
      ],
      "ip": 0,
      "op": 4.00000016292334,
      "st": 0,
      "ct": 1,
      "bm": 0
    }
  ],
  "markers": []
}
